{
  "id": "26089",
  "title": "日产万字、48 小时写完 500 万字：AI “文学平替”正重塑网文生态",
  "author": "",
  "publish_time": "2026-03-10 15:50",
  "url": "https://news.aibase.cn/zh/news/26089",
  "summary": "2026年网文界面临AI冲击，AI写作工具以千倍速度挑战人类作者。传统“爆肝”日更模式在AI“工业化生产”面前显得无力，引发行业生存危机。",
  "content_html": "<p>在 2026 年的网文江湖，一场关于“代码与灵魂”的较量已进入白热化。随着<response-element><link-block>AI 大模型</link-block></response-element>技术的突飞猛进，原本靠“爆肝”生存的网文作者们惊恐地发现，不知疲倦的<response-element><link-block>AI 写作工具</link-block></response-element>正在以千倍的速度入侵他们的领地。</p><p><strong>降维打击：AI 的“工业化生产”VS 人类的“爆肝”</strong></p><p>过去，日更一万字已被视为网文圈的“大神”级别，但在 AI 面前，这种努力显得微不足道。像<response-element><link-block>唐库</link-block></response-element>这样的全自动小说生成平台，宣称能在 48 小时内产出 500 万字的长篇小说。从世界观搭建到大纲细化，AI 几乎实现了全流程自动化。</p><p>这种效率上的“降维打击”已直接反映在平台数据上。据业内人士透露，<response-element><link-block>番茄小说</link-block></response-element>全站日首秀数据曾在一个月内从百位数飙升至突破五千。不少参与测试的作者感慨：“感觉 AI 比人类更懂网文套路，我们即将被淘汰。”</p><p><strong>灵魂拷问：是文学创作，还是“赛博预制菜”？</strong></p><p>尽管 AI 在数量上占尽优势，但其作品的质量却引发了广泛争议。<response-element><link-block>网文编辑乔欢</link-block></response-element>发现，AI 生成的内容往往逻辑工整、用词正确，却极度“平庸”，缺乏人类情感的真实表达。她将其形容为流水线生产的“预制菜”：尝一口就知道不是厨师现炒的。</p><p><response-element><link-block>图灵奖得主莫言</link-block></response-element>曾分享使用 AI 写诗的经历，认为 AI 虽能模仿风格，但缺乏真正的思想和创造性。目前，<response-element><link-block>晋江文学城</link-block></response-element>等平台仍坚持原创阵地，对 AI 生成作品持谨慎甚至拒绝态度，防止这些缺乏“人味儿”的作品透支读者的审美。</p><p><strong>平台抉择：创作者沦为机器的“化肥”？</strong></p><p>AI 时代的利益分配也成了矛盾焦点。去年，<response-element><link-block>番茄小说</link-block></response-element>的“AI 训练补充协议”曾引发轩然大波，作者们质疑自己的心血被当作滋养机器的“化肥”。虽然平台最终妥协，但人类原创者的核心价值在 AI 浪潮中如何安放，依然是行业未解的难题。</p><p><strong>未来的十字路口：共存还是取代？</strong></p><p><response-element><link-block>科幻作家刘慈欣</link-block></response-element>预测，未来 10 到 20 年，AI 极有可能在大比例上取代人类文学创作。而<response-element><link-block>首都师范大学学者许苗苗</link-block></response-element>则认为，AI 只能替代平庸之作，无法产生真正的文学精品。</p><p>在这个“万物皆可 AI”的 2026 年，网络文学正站在十字路口。是利用 AI 释放生产力，让作者回归创意核心？还是任由“预制菜”泛滥，最终毁掉原创的根基？这场技术与文学的博弈，才刚刚拉开大幕。</p><p><br/></p>",
  "content_text": "在 2026 年的网文江湖，一场关于“代码与灵魂”的较量已进入白热化。随着AI 大模型技术的突飞猛进，原本靠“爆肝”生存的网文作者们惊恐地发现，不知疲倦的AI 写作工具正在以千倍的速度入侵他们的领地。\n\n降维打击：AI 的“工业化生产”VS 人类的“爆肝”\n\n过去，日更一万字已被视为网文圈的“大神”级别，但在 AI 面前，这种努力显得微不足道。像唐库这样的全自动小说生成平台，宣称能在 48 小时内产出 500 万字的长篇小说。从世界观搭建到大纲细化，AI 几乎实现了全流程自动化。\n\n这种效率上的“降维打击”已直接反映在平台数据上。据业内人士透露，番茄小说全站日首秀数据曾在一个月内从百位数飙升至突破五千。不少参与测试的作者感慨：“感觉 AI 比人类更懂网文套路，我们即将被淘汰。”\n\n灵魂拷问：是文学创作，还是“赛博预制菜”？\n\n尽管 AI 在数量上占尽优势，但其作品的质量却引发了广泛争议。网文编辑乔欢发现，AI 生成的内容往往逻辑工整、用词正确，却极度“平庸”，缺乏人类情感的真实表达。她将其形容为流水线生产的“预制菜”：尝一口就知道不是厨师现炒的。\n\n图灵奖得主莫言曾分享使用 AI 写诗的经历，认为 AI 虽能模仿风格，但缺乏真正的思想和创造性。目前，晋江文学城等平台仍坚持原创阵地，对 AI 生成作品持谨慎甚至拒绝态度，防止这些缺乏“人味儿”的作品透支读者的审美。\n\n平台抉择：创作者沦为机器的“化肥”？\n\nAI 时代的利益分配也成了矛盾焦点。去年，番茄小说的“AI 训练补充协议”曾引发轩然大波，作者们质疑自己的心血被当作滋养机器的“化肥”。虽然平台最终妥协，但人类原创者的核心价值在 AI 浪潮中如何安放，依然是行业未解的难题。\n\n未来的十字路口：共存还是取代？\n\n科幻作家刘慈欣预测，未来 10 到 20 年，AI 极有可能在大比例上取代人类文学创作。而首都师范大学学者许苗苗则认为，AI 只能替代平庸之作，无法产生真正的文学精品。\n\n在这个“万物皆可 AI”的 2026 年，网络文学正站在十字路口。是利用 AI 释放生产力，让作者回归创意核心？还是任由“预制菜”泛滥，最终毁掉原创的根基？这场技术与文学的博弈，才刚刚拉开大幕。",
  "fetch_time": "2026-03-10 23:30:31"
}